Metadata-Version: 1.0
Name: autoDATA-prep
Version: 1.5.0
Summary: Data pre-processing library
Home-page: UNKNOWN
Author: Emmanuel Ezenwere
Author-email: emmaezenwere@gmail.com
License: UNKNOWN
Platform: UNKNOWN
